Metadata-Version: 2.4
Name: schema-dictionary-matcher
Version: 1.0.0
Summary: Production-ready semantic schema matching with sub-100ms latency
Author-email: Pierce Lonergan <lonerganpierce@gmail.com>
License: MIT
Requires-Python: >=3.11
License-File: LICENSE
Requires-Dist: sentence-transformers>=2.2.2
Requires-Dist: torch>=2.1.0
Requires-Dist: transformers>=4.35.0
Requires-Dist: qdrant-client>=1.7.0
Requires-Dist: pandas>=2.1.0
Requires-Dist: openpyxl>=3.1.2
Requires-Dist: numpy>=1.24.3
Requires-Dist: rank-bm25>=0.2.2
Requires-Dist: rapidfuzz>=3.5.2
Requires-Dist: pydantic>=2.5.0
Requires-Dist: tqdm>=4.66.0
Provides-Extra: api
Requires-Dist: fastapi>=0.104.1; extra == "api"
Requires-Dist: uvicorn[standard]>=0.24.0; extra == "api"
Requires-Dist: prometheus-client>=0.19.0; extra == "api"
Requires-Dist: python-multipart>=0.0.6; extra == "api"
Dynamic: license-file
